hopper_api-stubs/__init__.pyi
hopper_api-stubs/py.typed
types_hopper_disassembler-1.0.0.dist-info/licenses/LICENSE
types_hopper_disassembler-1.0.0.dist-info/METADATA
types_hopper_disassembler-1.0.0.dist-info/WHEEL
types_hopper_disassembler-1.0.0.dist-info/top_level.txt
types_hopper_disassembler-1.0.0.dist-info/RECORD
