Metadata-Version: 2.4
Name: types-hopper-disassembler
Version: 1.0.0
Summary: Type stubs for Hopper Disassembler Python API
Author-email: Fi5t <fi5t@pm.me>
License-Expression: MIT
Project-URL: Homepage, https://github.com/fi5t/hopper-disassembler-stubs
Project-URL: Repository, https://github.com/fi5t/hopper-disassembler-stubs
Project-URL: Issues, https://github.com/fi5t/hopper-disassembler-stubs/issues
Keywords: hopper,disassembler,stubs
Classifier: Intended Audience :: Developers
Classifier: Programming Language :: Python
Classifier: Programming Language :: Python :: 3
Classifier: Typing :: Typed
Requires-Python: >=3.8
License-File: LICENSE
Provides-Extra: dev
Requires-Dist: black; extra == "dev"
Requires-Dist: bumpver; extra == "dev"
Requires-Dist: isort; extra == "dev"
Requires-Dist: pytest; extra == "dev"
Dynamic: license-file
